occystrap/__init__.py
occystrap/common.py
occystrap/constants.py
occystrap/docker_extract.py
occystrap/docker_registry.py
occystrap/main.py
occystrap/output_directory.py
occystrap/output_mounts.py
occystrap/output_ocibundle.py
occystrap/output_tarfile.py
occystrap/util.py
occystrap/tests/__init__.py
occystrap-0.4.0.dist-info/AUTHORS
occystrap-0.4.0.dist-info/LICENSE
occystrap-0.4.0.dist-info/METADATA
occystrap-0.4.0.dist-info/WHEEL
occystrap-0.4.0.dist-info/entry_points.txt
occystrap-0.4.0.dist-info/pbr.json
occystrap-0.4.0.dist-info/top_level.txt
occystrap-0.4.0.dist-info/RECORD
