Metadata-Version: 2.1
Name: occystrap
Version: 0.4.0
Summary: occystrap: docker and OCI container tools
Home-page: https://github.com/shakenfist/occystrap
Author: Michael Still
Author-email: mikal@stillhq.com
License: Apache2
Platform: UNKNOWN
Classifier: Intended Audience :: Information Technology
Classifier: Intended Audience :: System Administrators
Classifier: License :: OSI Approved :: Apache Software License
Classifier: Operating System :: POSIX :: Linux
Classifier: Programming Language :: Python
Classifier: Programming Language :: Python :: 3
Classifier: Programming Language :: Python :: 3.7
Requires-Dist: click (>=7.1.1)
Requires-Dist: oslo.concurrency
Requires-Dist: pbr
Requires-Dist: prettytable
Requires-Dist: requests
Requires-Dist: shakenfist-utilities
